bakasur/__init__.py
bakasur/constants.py
bakasur/dashboard.py
bakasur/database.py
bakasur/exceptions.py
bakasur/helpers.py
bakasur/main.py
bakasur/utils.py
bakasur-1.3.2.dist-info/LICENSE.md
bakasur-1.3.2.dist-info/METADATA
bakasur-1.3.2.dist-info/WHEEL
bakasur-1.3.2.dist-info/entry_points.txt
bakasur-1.3.2.dist-info/RECORD
