Metadata-Version: 2.1
Name: bakasur
Version: 1.3.2
Summary: Bakasur is your friendly demon that helps you analyse your Thuisbezorgd order history and visualise patterns.
Author: Devendra Kulkarni
Author-email: kulkarnidevendra21@gmail.com
Requires-Python: >=3.8.0,<3.13.0
Classifier: Programming Language :: Python :: 3
Classifier: Programming Language :: Python :: 3.8
Classifier: Programming Language :: Python :: 3.9
Classifier: Programming Language :: Python :: 3.10
Classifier: Programming Language :: Python :: 3.11
Classifier: Programming Language :: Python :: 3.12
Requires-Dist: datapane (==0.17.0)
Requires-Dist: fake-useragent (>=1.1.1,<2.0.0)
Requires-Dist: requests (>=2.28.1,<3.0.0)
Requires-Dist: rich (>=12.4.4,<13.0.0)
Requires-Dist: typer[all] (>=0.4.2,<0.5.0)
